kadb/__init__.py
kadb/cli.py
kadb-0.1.0.dist-info/METADATA
kadb-0.1.0.dist-info/WHEEL
kadb-0.1.0.dist-info/entry_points.txt
kadb-0.1.0.dist-info/top_level.txt
kadb-0.1.0.dist-info/RECORD
