Metadata-Version: 2.4
Name: kadb
Version: 0.1.0
Summary: Outil pour déboguer Flutter/Android en Wi-Fi sans câble
Author-email: Koulibaly Amadou <koulibalyamadou10@gmail.com>
